<?xml version="1.0" encoding="UTF-8"?>
<metadata xml:lang="el"><Esri><CreaDate>20190918</CreaDate><CreaTime>13202200</CreaTime><ArcGISFormat>1.0</ArcGISFormat><SyncOnce>TRUE</SyncOnce><DataProperties><lineage><Process ToolSource="c:\program files (x86)\arcgis\desktop10.4\ArcToolbox\Toolboxes\Data Management Tools.tbx\CalculateField" Date="20190411" Time="103803">CalculateField CG_CY_Rocky_100m t "50-100" VB #</Process><Process ToolSource="c:\program files (x86)\arcgis\desktop10.4\ArcToolbox\Toolboxes\Data Management Tools.tbx\CalculateField" Date="20190411" Time="103829">CalculateField CG_CY_Rocky_100m t 0 VB #</Process><Process ToolSource="c:\program files (x86)\arcgis\desktop10.4\ArcToolbox\Toolboxes\Data Management Tools.tbx\CalculateField" Date="20190411" Time="103856">CalculateField CG_CY_Rocky_100m t "1-10" VB #</Process><Process ToolSource="c:\program files (x86)\arcgis\desktop10.4\ArcToolbox\Toolboxes\Data Management Tools.tbx\CalculateField" Date="20190411" Time="103921">CalculateField CG_CY_Rocky_100m t "10-50" VB #</Process><Process ToolSource="c:\program files (x86)\arcgis\desktop10.4\ArcToolbox\Toolboxes\Data Management Tools.tbx\CalculateField" Date="20190411" Time="103946">CalculateField CG_CY_Rocky_100m Percentage [t] VB #</Process><Process ToolSource="c:\program files (x86)\arcgis\desktop10.4\ArcToolbox\Toolboxes\Data Management Tools.tbx\CalculateField" Date="20190411" Time="113745">CalculateField CG_CY_Rocky_100m id [FID] VB #</Process></lineage><itemProps><itemLocation><linkage Sync="TRUE">file://\\MATINA-PC\C$\RECONNECT\reconnect_to_geoserver\Cyprus_Rocky\CG_CY_Rocky_100m</linkage><protocol Sync="TRUE">Local Area Network</protocol></itemLocation></itemProps><copyHistory><copy source="C:\RECONNECT\reconnect_to_geoserver\wgs84\CG_CY_Rocky_100m" dest="\\MATINA-PC\C$\RECONNECT\reconnect_to_geoserver\Cyprus_Rocky\CG_CY_Rocky_100m" date="20190918" time="13202200"></copy></copyHistory></DataProperties><ArcGISstyle>INSPIRE Metadata Directive</ArcGISstyle></Esri></metadata>
